nova/__init__.py
nova/trame/__init__.py
nova/trame/_internal/utils.py
nova/trame/model/data_selector.py
nova/trame/model/remote_file_input.py
nova/trame/model/ornl/analysis_data_selector.py
nova/trame/model/ornl/neutron_data_selector.py
nova/trame/model/ornl/oncat_data_selector.py
nova/trame/utils/types.py
nova/trame/view/components/__init__.py
nova/trame/view/components/data_selector.py
nova/trame/view/components/execution_buttons.py
nova/trame/view/components/file_upload.py
nova/trame/view/components/input_field.py
nova/trame/view/components/progress_bar.py
nova/trame/view/components/remote_file_input.py
nova/trame/view/components/tool_outputs.py
nova/trame/view/components/ornl/__init__.py
nova/trame/view/components/ornl/neutron_data_selector.py
nova/trame/view/components/visualization/__init__.py
nova/trame/view/components/visualization/interactive_2d_plot.py
nova/trame/view/components/visualization/matplotlib_figure.py
nova/trame/view/layouts/__init__.py
nova/trame/view/layouts/grid.py
nova/trame/view/layouts/hbox.py
nova/trame/view/layouts/utils.py
nova/trame/view/layouts/vbox.py
nova/trame/view/theme/__init__.py
nova/trame/view/theme/exit_button.py
nova/trame/view/theme/theme.py
nova/trame/view/theme/assets/core_style.scss
nova/trame/view/theme/assets/favicon.png
nova/trame/view/theme/assets/vuetify_config.json
nova/trame/view/theme/assets/js/delay_manager.js
nova/trame/view/theme/assets/js/lodash.min.js
nova/trame/view/theme/assets/js/revo_grid.js
nova/trame/view/utilities/local_storage.py
nova/trame/view_model/data_selector.py
nova/trame/view_model/execution_buttons.py
nova/trame/view_model/progress_bar.py
nova/trame/view_model/remote_file_input.py
nova/trame/view_model/tool_outputs.py
nova/trame/view_model/ornl/neutron_data_selector.py
nova_trame-1.3.5.dist-info/METADATA
nova_trame-1.3.5.dist-info/WHEEL
nova_trame-1.3.5.dist-info/licenses/LICENSE
nova_trame-1.3.5.dist-info/RECORD
