Metadata-Version: 2.4
Name: nova-trame
Version: 1.3.5
Summary: A Python Package for injecting curated themes and custom components into Trame applications
Project-URL: Changelog, https://code.ornl.gov/ndip/public-packages/nova-trame/blob/main/CHANGELOG.md
Author-email: John Duggan <dugganjw@ornl.gov>, Kristin Maroun <ponsonbykr@ornl.gov>, Sergey Yakubov <yakubovs@ornl.gov>, Gregory Cage <cagege@ornl.gov>
License-Expression: MIT
License-File: LICENSE
Keywords: NDIP,Python,Trame,Vuetify
Requires-Python: <3.14,>=3.10
Requires-Dist: altair
Requires-Dist: blinker<2,>=1.9.0
Requires-Dist: libsass
Requires-Dist: mergedeep
Requires-Dist: mpld3<0.6,>=0.5.11
Requires-Dist: natsort<9,>=8.4.0
Requires-Dist: nova-common>=0.2.2
Requires-Dist: nova-mvvm
Requires-Dist: oauthlib
Requires-Dist: pydantic
Requires-Dist: pyoncat<3,>=2.1
Requires-Dist: requests-oauthlib
Requires-Dist: tomli
Requires-Dist: tornado>=6.5.0
Requires-Dist: trame
Requires-Dist: trame-datagrid
Requires-Dist: trame-matplotlib
Requires-Dist: trame-plotly
Requires-Dist: trame-vega
Requires-Dist: trame-vuetify
